env_colab_pass/__init__.py
env_colab_pass/passutil.py
env_colab_pass-0.3.dist-info/LICENSE
env_colab_pass-0.3.dist-info/METADATA
env_colab_pass-0.3.dist-info/WHEEL
env_colab_pass-0.3.dist-info/top_level.txt
env_colab_pass-0.3.dist-info/RECORD
