Metadata-Version: 2.1
Name: env-colab-pass
Version: 0.3
Summary: Python library that check for key value in env and colab userdata. if not found then asks for it using getpass
Home-page: https://github.com/bkakadiya/env-colab-pass
Author: Bakulkumar Kakadiya
Author-email: bakul.kumar@gmail.com
License: Apache License Version 2.0
License-File: LICENSE
Provides-Extra: google-colab
Requires-Dist: google-colab ; extra == 'google-colab'
